{
  "parent": "minecraft:recipes/root",
  "criteria": {
    "has_485_black_apple": {
      "conditions": {
        "items": [
          {
            "items": [
              "betternether:black_apple"
            ]
          }
        ]
      },
      "trigger": "minecraft:inventory_changed"
    },
    "has_the_recipe": {
      "conditions": {
        "recipe": "betternether:black_apple_seed"
      },
      "trigger": "minecraft:recipe_unlocked"
    }
  },
  "display": {
    "announce_to_chat": false,
    "description": {
      "translate": "advancements.betternether.recipes/decorations/black_apple_seed.description"
    },
    "frame": "task",
    "hidden": false,
    "icon": {
      "item": "betternether:black_apple_seed"
    },
    "show_toast": false,
    "title": {
      "translate": "advancements.betternether.recipes/decorations/black_apple_seed.title"
    }
  },
  "requirements": [
    [
      "has_485_black_apple",
      "has_the_recipe"
    ]
  ],
  "rewards": {
    "recipes": [
      "betternether:black_apple_seed"
    ]
  }
}