{
  "parent": "minecraft:recipes/root",
  "criteria": {
    "has_266_rubeus_planks": {
      "conditions": {
        "items": [
          {
            "items": [
              "betternether:rubeus_planks"
            ]
          }
        ]
      },
      "trigger": "minecraft:inventory_changed"
    },
    "has_267_stick": {
      "conditions": {
        "items": [
          {
            "items": [
              "minecraft:stick"
            ]
          }
        ]
      },
      "trigger": "minecraft:inventory_changed"
    },
    "has_the_recipe": {
      "conditions": {
        "recipe": "betternether:rubeus_gate"
      },
      "trigger": "minecraft:recipe_unlocked"
    }
  },
  "display": {
    "announce_to_chat": false,
    "description": {
      "translate": "advancements.betternether.recipes/decorations/rubeus_gate.description"
    },
    "frame": "task",
    "hidden": false,
    "icon": {
      "item": "betternether:rubeus_gate"
    },
    "show_toast": false,
    "title": {
      "translate": "advancements.betternether.recipes/decorations/rubeus_gate.title"
    }
  },
  "requirements": [
    [
      "has_266_rubeus_planks",
      "has_267_stick",
      "has_the_recipe"
    ]
  ],
  "rewards": {
    "recipes": [
      "betternether:rubeus_gate"
    ]
  }
}