{
  "parent": "minecraft:recipes/root",
  "criteria": {
    "has_stone": {
      "conditions": {
        "items": [
          {
            "items": "minecraft:stone"
          }
        ]
      },
      "trigger": "minecraft:inventory_changed"
    },
    "has_tag_c_iron_ingots": {
      "conditions": {
        "items": [
          {
            "items": "#c:iron_ingots"
          }
        ]
      },
      "trigger": "minecraft:inventory_changed"
    },
    "has_the_recipe": {
      "conditions": {
        "recipe": "bclib:tag_stonecutter"
      },
      "trigger": "minecraft:recipe_unlocked"
    }
  },
  "requirements": [
    [
      "has_the_recipe",
      "has_stone",
      "has_tag_c_iron_ingots"
    ]
  ],
  "rewards": {
    "recipes": [
      "bclib:tag_stonecutter"
    ]
  }
}